LICENSE.txt
MANIFEST.in
README.rst
VERSION.txt
setup.cfg
setup.py
docs/source/changelog.rst
hubspot/__init__.py
hubspot/contacts/__init__.py
hubspot/contacts/_constants.py
hubspot/contacts/_data_retrieval.py
hubspot/contacts/_property_utils.py
hubspot/contacts/exc.py
hubspot/contacts/generic_utils.py
hubspot/contacts/lists.py
hubspot/contacts/properties.py
hubspot/contacts/property_groups.py
hubspot/contacts/testing.py
hubspot/contacts/_schemas/__init__.py
hubspot/contacts/_schemas/_validators.py
hubspot/contacts/_schemas/contacts.py
hubspot/contacts/_schemas/lists.py
hubspot/contacts/_schemas/properties.py
hubspot/contacts/request_data_formatters/__init__.py
hubspot/contacts/request_data_formatters/contacts.py
hubspot/contacts/request_data_formatters/properties.py
hubspot/contacts/request_data_formatters/property_groups.py
hubspot_contacts.egg-info/PKG-INFO
hubspot_contacts.egg-info/SOURCES.txt
hubspot_contacts.egg-info/dependency_links.txt
hubspot_contacts.egg-info/namespace_packages.txt
hubspot_contacts.egg-info/requires.txt
hubspot_contacts.egg-info/top_level.txt