Metadata-Version: 1.1
Name: hubspot-contacts
Version: 1.0rc2
Summary: Pythonic wrapper for HubSpot API methods in the Contacts, Contact Lists and Contact Properties APIs
Home-page: http://pythonhosted.org/hubspot-contacts/
Author: 2degrees Limited
Author-email: 2degrees-floss@googlegroups.com
License: BSD (http://dev.2degreesnetwork.com/p/2degrees-license.html)
Keywords: hubspot contacts lists properties
Platform: UNKNOWN
Classifier: Development Status :: 5 - Production/Stable
Classifier: Intended Audience :: Developers
Classifier: License :: OSI Approved :: BSD License
Classifier: Natural Language :: English
Classifier: Programming Language :: Python
